AxiomX/__init__.py
AxiomX/calculus.py
AxiomX/constants.py
AxiomX/exp.py
AxiomX/functions.py
AxiomX/hyperbolic.py
AxiomX/trig.py
axiomx-0.1.0.dist-info/licenses/LICENSE
axiomx-0.1.0.dist-info/METADATA
axiomx-0.1.0.dist-info/WHEEL
axiomx-0.1.0.dist-info/top_level.txt
axiomx-0.1.0.dist-info/RECORD
