Metadata-Version: 2.4
Name: AxiomX
Version: 0.1.0
Summary: A dynamic Python math library containing numerous mathematical functions implemented from scratch.
Author: Eric Joseph
License: MIT
Requires-Python: >=2.7
License-File: LICENSE
Dynamic: license-file
Dynamic: requires-python
